{
    "sourceFile": "work.html",
    "activeCommit": 0,
    "commits": [
        {
            "activePatchIndex": 13,
            "patches": [
                {
                    "date": 1644165808263,
                    "content": "Index: \n===================================================================\n--- \n+++ \n"
                },
                {
                    "date": 1644184138357,
                    "content": "Index: \n===================================================================\n--- \n+++ \n@@ -16,8 +16,9 @@\n     <link href=\"https://fonts.googleapis.com/css2?family=Roboto&display=swap\" rel=\"stylesheet\">\n     <link href=\"https://fonts.googleapis.com/css2?family=Six+Caps&display=swap\" rel=\"stylesheet\">\n     <!--Connects css to html-->\n     <link rel=\"stylesheet\" href=\"./styling/styles.css\">\n+    <link rel=\"stylesheet\" href=\"./styling/styles.css\">\n </head>\n <!--This contains all the content of the HTML document, such as headings, paragraphs,images,hyperlinks etc-->\n \n <body>\n"
                },
                {
                    "date": 1644185147132,
                    "content": "Index: \n===================================================================\n--- \n+++ \n@@ -16,9 +16,9 @@\n     <link href=\"https://fonts.googleapis.com/css2?family=Roboto&display=swap\" rel=\"stylesheet\">\n     <link href=\"https://fonts.googleapis.com/css2?family=Six+Caps&display=swap\" rel=\"stylesheet\">\n     <!--Connects css to html-->\n     <link rel=\"stylesheet\" href=\"./styling/styles.css\">\n-    <link rel=\"stylesheet\" href=\"./styling/styles.css\">\n+    <link rel=\"stylesheet\" href=\"./styling/work.css\">\n </head>\n <!--This contains all the content of the HTML document, such as headings, paragraphs,images,hyperlinks etc-->\n \n <body>\n@@ -33,14 +33,33 @@\n             <!-- This container holds the logo and navigation bar for the various pages on the website.Uses flexbox-->\n             <nav class=\"navbar\">\n                 <!-- This container holds the links and uses flexbox with space around the links-->\n                 <div class=\"nav-links\">\n-                    <a class=\"nav-link\" href=\"index.html\">Home</a>\n                     <!--This navigation link is selected and has its own styling-->\n-                    <a class=\"nav-link selected-link\" href=\"work.html\">Work</a>\n-                    <a class=\"nav-link\" href=\"contact.html\">Contact</a>\n-                    <a class=\"nav-link\" href=\"about.html\">About</a>\n+                    <ul class=\"not-mobile\">\n+                        <li><a class=\"nav-link selected-link\" href=\"index.html\">Home</a></li>\n+                        <li><a class=\"nav-link\" href=\"work.html\">Work</a></li>\n+                        <li><a class=\"nav-link\" href=\"contact.html\">Contact</a></li>\n+                        <li><a class=\"nav-link\" href=\"about.html\">About</a></li>\n+                    </ul>\n+\n+                    <button onclick=\"openSideNav()\" type=\"button\"\n+                        class=\"btn btn-flat button-ripple flex-center only-mobile\">\n+                        <span class=\"material-icons md-36\">menu</span>\n+                    </button>\n                 </div>\n+                <div class=\"nav-drawer\">\n+                    <button onclick=\"closeSideNav()\" type=\"button\" class=\"btn btn-flat button-ripple flex-center\">\n+                        <span class=\"material-icons md-36\">close</span>\n+                    </button>\n+                    <!--This navigation link is selected and has its own styling-->\n+                    <ul>\n+                        <li><a class=\"nav-link selected-link\" href=\"index.html\">Home</a></li>\n+                        <li><a class=\"nav-link\" href=\"work.html\">Work</a></li>\n+                        <li><a class=\"nav-link\" href=\"contact.html\">Contact</a></li>\n+                        <li><a class=\"nav-link\" href=\"about.html\">About</a></li>\n+                    </ul>\n+                </div>\n             </nav>\n             <div class=\"content-flex\">\n                 <!--This container holds the work-picture. Sets size to the picture and has position relative-->\n                 <div class=\"work-pic\">\n"
                },
                {
                    "date": 1644185198296,
                    "content": "Index: \n===================================================================\n--- \n+++ \n@@ -12,8 +12,9 @@\n     <!--This is telling the browser what scaling and dimensions the viewport should have-->\n     <meta name=\"viewport\" content=\"width=device-width, initial-scale=1.0\">\n     <!--Name of the page in the tab-->\n     <title>Work</title>\n+    <link href=\"https://fonts.googleapis.com/icon?family=Material+Icons\" rel=\"stylesheet\">\n     <link href=\"https://fonts.googleapis.com/css2?family=Roboto&display=swap\" rel=\"stylesheet\">\n     <link href=\"https://fonts.googleapis.com/css2?family=Six+Caps&display=swap\" rel=\"stylesheet\">\n     <!--Connects css to html-->\n     <link rel=\"stylesheet\" href=\"./styling/styles.css\">\n"
                },
                {
                    "date": 1644185242514,
                    "content": "Index: \n===================================================================\n--- \n+++ \n@@ -97,6 +97,7 @@\n                 <img class=\"socialmedia-icon\" src=\"img/linkedin.svg\" />\n             </a>\n         </div>\n </body>\n+<script src=\"javascript.js\"></script>\n \n </html>\n\\ No newline at end of file\n"
                },
                {
                    "date": 1644185282973,
                    "content": "Index: \n===================================================================\n--- \n+++ \n@@ -53,9 +53,9 @@\n                         <span class=\"material-icons md-36\">close</span>\n                     </button>\n                     <!--This navigation link is selected and has its own styling-->\n                     <ul>\n-                        <li><a class=\"nav-link selected-link\" href=\"index.html\">Home</a></li>\n+                        <li><a class=\"nav-link\" href=\"index.html\">Home</a></li>\n                         <li><a class=\"nav-link\" href=\"work.html\">Work</a></li>\n                         <li><a class=\"nav-link\" href=\"contact.html\">Contact</a></li>\n                         <li><a class=\"nav-link\" href=\"about.html\">About</a></li>\n                     </ul>\n"
                },
                {
                    "date": 1644186467031,
                    "content": "Index: \n===================================================================\n--- \n+++ \n@@ -54,9 +54,9 @@\n                     </button>\n                     <!--This navigation link is selected and has its own styling-->\n                     <ul>\n                         <li><a class=\"nav-link\" href=\"index.html\">Home</a></li>\n-                        <li><a class=\"nav-link\" href=\"work.html\">Work</a></li>\n+                        <li><a class=\"nav-link selected-link\" href=\"work.html\">Work</a></li>\n                         <li><a class=\"nav-link\" href=\"contact.html\">Contact</a></li>\n                         <li><a class=\"nav-link\" href=\"about.html\">About</a></li>\n                     </ul>\n                 </div>\n@@ -78,9 +78,9 @@\n                         so I was able to learn collaborative skills.\n                     </p>\n                     <!--This container holds the hyperlynk button to the prototype in Figma. -->\n \n-                    <!-- <a href=\"https://www.figma.com/proto/K0xFACAk3Rpqk1qMivZfE3/Untitled?page-id=0%3A1&node-id=2%3A63&viewport=241%2C48%2C0.2&scaling=scale-down&starting-point-node-id=2%3A63&show-proto-sidebar=1\"\n+                    <a href=\"https://www.figma.com/proto/K0xFACAk3Rpqk1qMivZfE3/Untitled?page-id=0%3A1&node-id=2%3A63&viewport=241%2C48%2C0.2&scaling=scale-down&starting-point-node-id=2%3A63&show-proto-sidebar=1\"\n                         class=\"button\">Prototype</a> -->\n                 </div>\n             </div>\n         </div>\n"
                },
                {
                    "date": 1644186613337,
                    "content": "Index: \n===================================================================\n--- \n+++ \n@@ -78,10 +78,10 @@\n                         so I was able to learn collaborative skills.\n                     </p>\n                     <!--This container holds the hyperlynk button to the prototype in Figma. -->\n \n-                    <a href=\"https://www.figma.com/proto/K0xFACAk3Rpqk1qMivZfE3/Untitled?page-id=0%3A1&node-id=2%3A63&viewport=241%2C48%2C0.2&scaling=scale-down&starting-point-node-id=2%3A63&show-proto-sidebar=1\"\n-                        class=\"button\">Prototype</a> -->\n+                    <!--a href=\"https://www.figma.com/proto/K0xFACAk3Rpqk1qMivZfE3/Untitled?page-id=0%3A1&node-id=2%3A63&viewport=241%2C48%2C0.2&scaling=scale-down&starting-point-node-id=2%3A63&show-proto-sidebar=1\"\n+                        class=\"button\">Prototype</a>\n                 </div>\n             </div>\n         </div>\n         <!--This container holds links to socialmedia.\n"
                },
                {
                    "date": 1644187851416,
                    "content": "Index: \n===================================================================\n--- \n+++ \n@@ -53,12 +53,32 @@\n                         <span class=\"material-icons md-36\">close</span>\n                     </button>\n                     <!--This navigation link is selected and has its own styling-->\n                     <ul>\n-                        <li><a class=\"nav-link\" href=\"index.html\">Home</a></li>\n-                        <li><a class=\"nav-link selected-link\" href=\"work.html\">Work</a></li>\n-                        <li><a class=\"nav-link\" href=\"contact.html\">Contact</a></li>\n-                        <li><a class=\"nav-link\" href=\"about.html\">About</a></li>\n+                        <li>\n+                            <a class=\"nav-link\" href=\"index.html\">Home</a>\n+                            <span>\n+                                <img src=\"./img/navigate_next_black_24dp.svg\">\n+                            </span>\n+                        </li>\n+                        <li>\n+                            <a class=\"nav-link\" href=\"work.html\">Work</a>\n+                            <span>\n+                                <img src=\"./img/navigate_next_black_24dp.svg\">\n+                            </span>\n+                        </li>\n+                        <li>\n+                            <a class=\"nav-link selected-link\" href=\"contact.html\">Contact</a>\n+                            <span>\n+                                <img src=\"./img/navigate_next_black_24dp.svg\">\n+                            </span>\n+                        </li>\n+                        <li>\n+                            <a class=\"nav-link\" href=\"about.html\">About</a>\n+                            <span>\n+                                <img src=\"./img/navigate_next_black_24dp.svg\">\n+                            </span>\n+                        </li>\n                     </ul>\n                 </div>\n             </nav>\n             <div class=\"content-flex\">\n@@ -79,9 +99,9 @@\n                     </p>\n                     <!--This container holds the hyperlynk button to the prototype in Figma. -->\n \n                     <!--a href=\"https://www.figma.com/proto/K0xFACAk3Rpqk1qMivZfE3/Untitled?page-id=0%3A1&node-id=2%3A63&viewport=241%2C48%2C0.2&scaling=scale-down&starting-point-node-id=2%3A63&show-proto-sidebar=1\"\n-                        class=\"button\">Prototype</a>\n+                        class=\"button\">Prototype</a-->\n                 </div>\n             </div>\n         </div>\n         <!--This container holds links to socialmedia.\n"
                },
                {
                    "date": 1644187905368,
                    "content": "Index: \n===================================================================\n--- \n+++ \n@@ -60,9 +60,9 @@\n                                 <img src=\"./img/navigate_next_black_24dp.svg\">\n                             </span>\n                         </li>\n                         <li>\n-                            <a class=\"nav-link\" href=\"work.html\">Work</a>\n+                            <a class=\"nav-link  selected-link\" href=\"work.html\">Work</a>\n                             <span>\n                                 <img src=\"./img/navigate_next_black_24dp.svg\">\n                             </span>\n                         </li>\n"
                },
                {
                    "date": 1644187933468,
                    "content": "Index: \n===================================================================\n--- \n+++ \n@@ -60,15 +60,15 @@\n                                 <img src=\"./img/navigate_next_black_24dp.svg\">\n                             </span>\n                         </li>\n                         <li>\n-                            <a class=\"nav-link  selected-link\" href=\"work.html\">Work</a>\n+                            <a class=\"nav-link selected-link\" href=\"work.html\">Work</a>\n                             <span>\n                                 <img src=\"./img/navigate_next_black_24dp.svg\">\n                             </span>\n                         </li>\n                         <li>\n-                            <a class=\"nav-link selected-link\" href=\"contact.html\">Contact</a>\n+                            <a class=\"nav-link\" href=\"contact.html\">Contact</a>\n                             <span>\n                                 <img src=\"./img/navigate_next_black_24dp.svg\">\n                             </span>\n                         </li>\n"
                },
                {
                    "date": 1644192146698,
                    "content": "Index: \n===================================================================\n--- \n+++ \n@@ -37,9 +37,9 @@\n                 <div class=\"nav-links\">\n                     <!--This navigation link is selected and has its own styling-->\n                     <ul class=\"not-mobile\">\n                         <li><a class=\"nav-link selected-link\" href=\"index.html\">Home</a></li>\n-                        <li><a class=\"nav-link\" href=\"work.html\">Work</a></li>\n+                        <li><a class= href=\"work.html\">Work</a></li>\n                         <li><a class=\"nav-link\" href=\"contact.html\">Contact</a></li>\n                         <li><a class=\"nav-link\" href=\"about.html\">About</a></li>\n                     </ul>\n \n"
                },
                {
                    "date": 1644192167946,
                    "content": "Index: \n===================================================================\n--- \n+++ \n@@ -36,10 +36,10 @@\n                 <!-- This container holds the links and uses flexbox with space around the links-->\n                 <div class=\"nav-links\">\n                     <!--This navigation link is selected and has its own styling-->\n                     <ul class=\"not-mobile\">\n-                        <li><a class=\"nav-link selected-link\" href=\"index.html\">Home</a></li>\n-                        <li><a class= href=\"work.html\">Work</a></li>\n+                        <li><a class= href=\"index.html\">Home</a></li>\n+                        <li><a class=\"nav-link selected-link\" href=\"work.html\">Work</a></li>\n                         <li><a class=\"nav-link\" href=\"contact.html\">Contact</a></li>\n                         <li><a class=\"nav-link\" href=\"about.html\">About</a></li>\n                     </ul>\n \n"
                },
                {
                    "date": 1644194998229,
                    "content": "Index: \n===================================================================\n--- \n+++ \n@@ -36,9 +36,9 @@\n                 <!-- This container holds the links and uses flexbox with space around the links-->\n                 <div class=\"nav-links\">\n                     <!--This navigation link is selected and has its own styling-->\n                     <ul class=\"not-mobile\">\n-                        <li><a class= href=\"index.html\">Home</a></li>\n+                        <li><a class=\"nav-link\" href=\"index.html\">Home</a></li>\n                         <li><a class=\"nav-link selected-link\" href=\"work.html\">Work</a></li>\n                         <li><a class=\"nav-link\" href=\"contact.html\">Contact</a></li>\n                         <li><a class=\"nav-link\" href=\"about.html\">About</a></li>\n                     </ul>\n@@ -61,11 +61,8 @@\n                             </span>\n                         </li>\n                         <li>\n                             <a class=\"nav-link selected-link\" href=\"work.html\">Work</a>\n-                            <span>\n-                                <img src=\"./img/navigate_next_black_24dp.svg\">\n-                            </span>\n                         </li>\n                         <li>\n                             <a class=\"nav-link\" href=\"contact.html\">Contact</a>\n                             <span>\n"
                }
            ],
            "date": 1644165808263,
            "name": "Commit-0",
            "content": "<!--Tells the browser that the type of content is HTML-->\n<!DOCTYPE html>\n<!--The root of the HTML structure with attribute setting the language to english-->\n<html lang=\"en\">\n<!--Contains all metadata that defines document title,styles and scripts -->\n\n<head>\n    <!--Charset attribute sets the first ascii encoding standard (UTF-8) -->\n    <meta charset=\"UTF-8\">\n    <!--Is used to set what version of internet explorer should be rendered as.This is set to highest most available mode-->\n    <meta http-equiv=\"X-UA-Compatible\" content=\"IE=edge\">\n    <!--This is telling the browser what scaling and dimensions the viewport should have-->\n    <meta name=\"viewport\" content=\"width=device-width, initial-scale=1.0\">\n    <!--Name of the page in the tab-->\n    <title>Work</title>\n    <link href=\"https://fonts.googleapis.com/css2?family=Roboto&display=swap\" rel=\"stylesheet\">\n    <link href=\"https://fonts.googleapis.com/css2?family=Six+Caps&display=swap\" rel=\"stylesheet\">\n    <!--Connects css to html-->\n    <link rel=\"stylesheet\" href=\"./styling/styles.css\">\n</head>\n<!--This contains all the content of the HTML document, such as headings, paragraphs,images,hyperlinks etc-->\n\n<body>\n    <!--This container holds all content and sets background color and size-->\n    <div class=\"background\">\n        <!-- This container holds the logo-->\n        <div class=logo-text>\n            <h1>Caroline Martinussen</p>\n        </div>\n        <!--This container holds the main content. Has its own background-color. Has position absolute-->\n        <div class=\"semi-background\">\n            <!-- This container holds the logo and navigation bar for the various pages on the website.Uses flexbox-->\n            <nav class=\"navbar\">\n                <!-- This container holds the links and uses flexbox with space around the links-->\n                <div class=\"nav-links\">\n                    <a class=\"nav-link\" href=\"index.html\">Home</a>\n                    <!--This navigation link is selected and has its own styling-->\n                    <a class=\"nav-link selected-link\" href=\"work.html\">Work</a>\n                    <a class=\"nav-link\" href=\"contact.html\">Contact</a>\n                    <a class=\"nav-link\" href=\"about.html\">About</a>\n                </div>\n            </nav>\n            <div class=\"content-flex\">\n                <!--This container holds the work-picture. Sets size to the picture and has position relative-->\n                <div class=\"work-pic\">\n                    <!-- This tag has the class image-fit to set max width and max height to its parent container-->\n                    <img class=\"image-fit\" src=\"img/interaksjonsdesign.png\">\n                </div>\n                <!--This container holds the text.Sets the size,font and color of the text.Has position absolute -->\n                <div class=\"text-work\">\n                    <p>\n                        The first project in the course Interaction design.\n                        This project introduced me to Figma.\n                        In addition to learning what interaction design was and\n                        how to use new programs,\n                        I was fortunate enough to work with a classmate on the project\n                        so I was able to learn collaborative skills.\n                    </p>\n                    <!--This container holds the hyperlynk button to the prototype in Figma. -->\n\n                    <!-- <a href=\"https://www.figma.com/proto/K0xFACAk3Rpqk1qMivZfE3/Untitled?page-id=0%3A1&node-id=2%3A63&viewport=241%2C48%2C0.2&scaling=scale-down&starting-point-node-id=2%3A63&show-proto-sidebar=1\"\n                        class=\"button\">Prototype</a> -->\n                </div>\n            </div>\n        </div>\n        <!--This container holds links to socialmedia.\n              Uses flexbox to set spacing between the links and the hight of the container.\n              Has position absolute-->\n        <div class=\"socialmedia-container\">\n            <a href=\"https://www.instagram.com/carolinemartinussen_/\">\n                <!-- This img tag has a class that is setting the size of the instagram image-->\n                <img class=\"socialmedia-icon\" src=\"img/instagram 1.svg\" />\n            </a>\n            <a href=\"https://www.linkedin.com/in/caroline-martinussen-819a98226/\">\n                <!-- This img tag has a class that is setting the size of the linkedin image-->\n                <img class=\"socialmedia-icon\" src=\"img/linkedin.svg\" />\n            </a>\n        </div>\n</body>\n\n</html>"
        }
    ]
}